{
  "title": "The Little Star Who Wanted to Shine on Christmas Eve",
  "author": "Traditional",
  "cover": "cover.jpeg",
  "audio": "audio.mp3",
  "youtube": "https://youtu.be/F3GztjdMa7Q",
  "content": [
    {
      "text": "**The Little Star Who Wanted to Shine on Christmas Eve**  Once upon a time, high up in the velvet sky, where the air was crisp and the clouds drifted like soft cotton candy, there lived a tiny star named Twink.",
      "side": "right",
      "start": 0.0,
      "end": 19.4,
      "image": "1_right.jpg",
      "words": [
        {
          "w": "**The",
          "s": 0.0,
          "e": 0.571
        },
        {
          "w": "Little",
          "s": 0.571,
          "e": 1.255
        },
        {
          "w": "Star",
          "s": 1.255,
          "e": 1.712
        },
        {
          "w": "Who",
          "s": 1.712,
          "e": 2.054
        },
        {
          "w": "Wanted",
          "s": 2.054,
          "e": 2.739
        },
        {
          "w": "to",
          "s": 2.739,
          "e": 2.967
        },
        {
          "w": "Shine",
          "s": 2.967,
          "e": 3.538
        },
        {
          "w": "on",
          "s": 3.538,
          "e": 3.766
        },
        {
          "w": "Christmas",
          "s": 3.766,
          "e": 4.793
        },
        {
          "w": "Eve**",
          "s": 4.793,
          "e": 5.364
        },
        {
          "w": "Once",
          "s": 5.364,
          "e": 5.82
        },
        {
          "w": "upon",
          "s": 5.82,
          "e": 6.276
        },
        {
          "w": "a",
          "s": 6.276,
          "e": 6.391
        },
        {
          "w": "time,",
          "s": 6.391,
          "e": 6.961
        },
        {
          "w": "high",
          "s": 6.961,
          "e": 7.418
        },
        {
          "w": "up",
          "s": 7.418,
          "e": 7.646
        },
        {
          "w": "in",
          "s": 7.646,
          "e": 7.874
        },
        {
          "w": "the",
          "s": 7.874,
          "e": 8.216
        },
        {
          "w": "velvet",
          "s": 8.216,
          "e": 8.901
        },
        {
          "w": "sky,",
          "s": 8.901,
          "e": 9.358
        },
        {
          "w": "where",
          "s": 9.358,
          "e": 9.928
        },
        {
          "w": "the",
          "s": 9.928,
          "e": 10.271
        },
        {
          "w": "air",
          "s": 10.271,
          "e": 10.613
        },
        {
          "w": "was",
          "s": 10.613,
          "e": 10.955
        },
        {
          "w": "crisp",
          "s": 10.955,
          "e": 11.526
        },
        {
          "w": "and",
          "s": 11.526,
          "e": 11.868
        },
        {
          "w": "the",
          "s": 11.868,
          "e": 12.211
        },
        {
          "w": "clouds",
          "s": 12.211,
          "e": 12.895
        },
        {
          "w": "drifted",
          "s": 12.895,
          "e": 13.694
        },
        {
          "w": "like",
          "s": 13.694,
          "e": 14.151
        },
        {
          "w": "soft",
          "s": 14.151,
          "e": 14.607
        },
        {
          "w": "cotton",
          "s": 14.607,
          "e": 15.292
        },
        {
          "w": "candy,",
          "s": 15.292,
          "e": 15.976
        },
        {
          "w": "there",
          "s": 15.976,
          "e": 16.547
        },
        {
          "w": "lived",
          "s": 16.547,
          "e": 17.118
        },
        {
          "w": "a",
          "s": 17.118,
          "e": 17.232
        },
        {
          "w": "tiny",
          "s": 17.232,
          "e": 17.688
        },
        {
          "w": "star",
          "s": 17.688,
          "e": 18.145
        },
        {
          "w": "named",
          "s": 18.145,
          "e": 18.715
        },
        {
          "w": "Twink.",
          "s": 18.715,
          "e": 19.4
        }
      ]
    },
    {
      "text": "Twink was the smallest star in the whole sky, no bigger than a snowflake, but she had the biggest, brightest dream of all.",
      "side": "left",
      "start": 19.4,
      "end": 29.76,
      "image": "2_left.jpg",
      "words": [
        {
          "w": "Twink",
          "s": 19.4,
          "e": 19.918
        },
        {
          "w": "was",
          "s": 19.918,
          "e": 20.229
        },
        {
          "w": "the",
          "s": 20.229,
          "e": 20.54
        },
        {
          "w": "smallest",
          "s": 20.54,
          "e": 21.368
        },
        {
          "w": "star",
          "s": 21.368,
          "e": 21.783
        },
        {
          "w": "in",
          "s": 21.783,
          "e": 21.99
        },
        {
          "w": "the",
          "s": 21.99,
          "e": 22.301
        },
        {
          "w": "whole",
          "s": 22.301,
          "e": 22.819
        },
        {
          "w": "sky,",
          "s": 22.819,
          "e": 23.233
        },
        {
          "w": "no",
          "s": 23.233,
          "e": 23.44
        },
        {
          "w": "bigger",
          "s": 23.44,
          "e": 24.062
        },
        {
          "w": "than",
          "s": 24.062,
          "e": 24.476
        },
        {
          "w": "a",
          "s": 24.476,
          "e": 24.58
        },
        {
          "w": "snowflake,",
          "s": 24.58,
          "e": 25.616
        },
        {
          "w": "but",
          "s": 25.616,
          "e": 25.927
        },
        {
          "w": "she",
          "s": 25.927,
          "e": 26.238
        },
        {
          "w": "had",
          "s": 26.238,
          "e": 26.548
        },
        {
          "w": "the",
          "s": 26.548,
          "e": 26.859
        },
        {
          "w": "biggest,",
          "s": 26.859,
          "e": 27.688
        },
        {
          "w": "brightest",
          "s": 27.688,
          "e": 28.62
        },
        {
          "w": "dream",
          "s": 28.62,
          "e": 29.138
        },
        {
          "w": "of",
          "s": 29.138,
          "e": 29.346
        },
        {
          "w": "all.",
          "s": 29.346,
          "e": 29.76
        }
      ]
    },
    {
      "text": "Every night, she watched as the other stars twinkled and gleamed, casting their golden light down upon the world below.",
      "side": "right",
      "start": 29.76,
      "end": 38.68,
      "image": "3_right.jpg",
      "words": [
        {
          "w": "Every",
          "s": 29.76,
          "e": 30.206
        },
        {
          "w": "night,",
          "s": 30.206,
          "e": 30.741
        },
        {
          "w": "she",
          "s": 30.741,
          "e": 31.009
        },
        {
          "w": "watched",
          "s": 31.009,
          "e": 31.633
        },
        {
          "w": "as",
          "s": 31.633,
          "e": 31.812
        },
        {
          "w": "the",
          "s": 31.812,
          "e": 32.079
        },
        {
          "w": "other",
          "s": 32.079,
          "e": 32.525
        },
        {
          "w": "stars",
          "s": 32.525,
          "e": 32.971
        },
        {
          "w": "twinkled",
          "s": 32.971,
          "e": 33.685
        },
        {
          "w": "and",
          "s": 33.685,
          "e": 33.952
        },
        {
          "w": "gleamed,",
          "s": 33.952,
          "e": 34.666
        },
        {
          "w": "casting",
          "s": 34.666,
          "e": 35.29
        },
        {
          "w": "their",
          "s": 35.29,
          "e": 35.736
        },
        {
          "w": "golden",
          "s": 35.736,
          "e": 36.272
        },
        {
          "w": "light",
          "s": 36.272,
          "e": 36.718
        },
        {
          "w": "down",
          "s": 36.718,
          "e": 37.074
        },
        {
          "w": "upon",
          "s": 37.074,
          "e": 37.431
        },
        {
          "w": "the",
          "s": 37.431,
          "e": 37.699
        },
        {
          "w": "world",
          "s": 37.699,
          "e": 38.145
        },
        {
          "w": "below.",
          "s": 38.145,
          "e": 38.68
        }
      ]
    },
    {
      "text": "But Twink’s favorite night of all was Christmas Eve, when the sky sparkled like a giant treasure chest, and the stars worked together to light the way for Santa’s sleigh.",
      "side": "left",
      "start": 38.68,
      "end": 49.88,
      "image": "4_left.jpg",
      "words": [
        {
          "w": "But",
          "s": 38.68,
          "e": 38.918
        },
        {
          "w": "Twink’s",
          "s": 38.918,
          "e": 39.474
        },
        {
          "w": "favorite",
          "s": 39.474,
          "e": 40.11
        },
        {
          "w": "night",
          "s": 40.11,
          "e": 40.507
        },
        {
          "w": "of",
          "s": 40.507,
          "e": 40.666
        },
        {
          "w": "all",
          "s": 40.666,
          "e": 40.904
        },
        {
          "w": "was",
          "s": 40.904,
          "e": 41.142
        },
        {
          "w": "Christmas",
          "s": 41.142,
          "e": 41.857
        },
        {
          "w": "Eve,",
          "s": 41.857,
          "e": 42.175
        },
        {
          "w": "when",
          "s": 42.175,
          "e": 42.493
        },
        {
          "w": "the",
          "s": 42.493,
          "e": 42.731
        },
        {
          "w": "sky",
          "s": 42.731,
          "e": 42.969
        },
        {
          "w": "sparkled",
          "s": 42.969,
          "e": 43.605
        },
        {
          "w": "like",
          "s": 43.605,
          "e": 43.923
        },
        {
          "w": "a",
          "s": 43.923,
          "e": 44.002
        },
        {
          "w": "giant",
          "s": 44.002,
          "e": 44.399
        },
        {
          "w": "treasure",
          "s": 44.399,
          "e": 45.035
        },
        {
          "w": "chest,",
          "s": 45.035,
          "e": 45.511
        },
        {
          "w": "and",
          "s": 45.511,
          "e": 45.75
        },
        {
          "w": "the",
          "s": 45.75,
          "e": 45.988
        },
        {
          "w": "stars",
          "s": 45.988,
          "e": 46.385
        },
        {
          "w": "worked",
          "s": 46.385,
          "e": 46.862
        },
        {
          "w": "together",
          "s": 46.862,
          "e": 47.497
        },
        {
          "w": "to",
          "s": 47.497,
          "e": 47.656
        },
        {
          "w": "light",
          "s": 47.656,
          "e": 48.053
        },
        {
          "w": "the",
          "s": 48.053,
          "e": 48.291
        },
        {
          "w": "way",
          "s": 48.291,
          "e": 48.53
        },
        {
          "w": "for",
          "s": 48.53,
          "e": 48.768
        },
        {
          "w": "Santa’s",
          "s": 48.768,
          "e": 49.324
        },
        {
          "w": "sleigh.",
          "s": 49.324,
          "e": 49.88
        }
      ]
    },
    {
      "text": "“Oh, how I wish I could shine on Christmas Eve!” Twink sighed, her little light flickering with excitement.",
      "side": "right",
      "start": 49.88,
      "end": 59.08,
      "image": "5_right.jpg",
      "words": [
        {
          "w": "“Oh,",
          "s": 49.88,
          "e": 50.289
        },
        {
          "w": "how",
          "s": 50.289,
          "e": 50.596
        },
        {
          "w": "I",
          "s": 50.596,
          "e": 50.698
        },
        {
          "w": "wish",
          "s": 50.698,
          "e": 51.107
        },
        {
          "w": "I",
          "s": 51.107,
          "e": 51.209
        },
        {
          "w": "could",
          "s": 51.209,
          "e": 51.72
        },
        {
          "w": "shine",
          "s": 51.72,
          "e": 52.231
        },
        {
          "w": "on",
          "s": 52.231,
          "e": 52.436
        },
        {
          "w": "Christmas",
          "s": 52.436,
          "e": 53.356
        },
        {
          "w": "Eve!”",
          "s": 53.356,
          "e": 53.867
        },
        {
          "w": "Twink",
          "s": 53.867,
          "e": 54.378
        },
        {
          "w": "sighed,",
          "s": 54.378,
          "e": 55.093
        },
        {
          "w": "her",
          "s": 55.093,
          "e": 55.4
        },
        {
          "w": "little",
          "s": 55.4,
          "e": 56.013
        },
        {
          "w": "light",
          "s": 56.013,
          "e": 56.524
        },
        {
          "w": "flickering",
          "s": 56.524,
          "e": 57.547
        },
        {
          "w": "with",
          "s": 57.547,
          "e": 57.956
        },
        {
          "w": "excitement.",
          "s": 57.956,
          "e": 59.08
        }
      ]
    },
    {
      "text": "“I want to help guide Santa’s sleigh just like the other stars!”  But the older stars, who had been shining for centuries, chuckled kindly.",
      "side": "left",
      "start": 59.08,
      "end": 71.12,
      "image": "6_left.jpg",
      "words": [
        {
          "w": "“I",
          "s": 59.08,
          "e": 59.289
        },
        {
          "w": "want",
          "s": 59.289,
          "e": 59.708
        },
        {
          "w": "to",
          "s": 59.708,
          "e": 59.918
        },
        {
          "w": "help",
          "s": 59.918,
          "e": 60.336
        },
        {
          "w": "guide",
          "s": 60.336,
          "e": 60.86
        },
        {
          "w": "Santa’s",
          "s": 60.86,
          "e": 61.593
        },
        {
          "w": "sleigh",
          "s": 61.593,
          "e": 62.221
        },
        {
          "w": "just",
          "s": 62.221,
          "e": 62.64
        },
        {
          "w": "like",
          "s": 62.64,
          "e": 63.058
        },
        {
          "w": "the",
          "s": 63.058,
          "e": 63.373
        },
        {
          "w": "other",
          "s": 63.373,
          "e": 63.896
        },
        {
          "w": "stars!”",
          "s": 63.896,
          "e": 64.629
        },
        {
          "w": "But",
          "s": 64.629,
          "e": 64.943
        },
        {
          "w": "the",
          "s": 64.943,
          "e": 65.257
        },
        {
          "w": "older",
          "s": 65.257,
          "e": 65.781
        },
        {
          "w": "stars,",
          "s": 65.781,
          "e": 66.409
        },
        {
          "w": "who",
          "s": 66.409,
          "e": 66.723
        },
        {
          "w": "had",
          "s": 66.723,
          "e": 67.037
        },
        {
          "w": "been",
          "s": 67.037,
          "e": 67.456
        },
        {
          "w": "shining",
          "s": 67.456,
          "e": 68.189
        },
        {
          "w": "for",
          "s": 68.189,
          "e": 68.503
        },
        {
          "w": "centuries,",
          "s": 68.503,
          "e": 69.55
        },
        {
          "w": "chuckled",
          "s": 69.55,
          "e": 70.387
        },
        {
          "w": "kindly.",
          "s": 70.387,
          "e": 71.12
        }
      ]
    },
    {
      "text": "“Oh, little one,” said Polaris, the great North Star, “you are far too small to be seen from the ground.",
      "side": "right",
      "start": 71.12,
      "end": 82.84,
      "image": "7_right.jpg",
      "words": [
        {
          "w": "“Oh,",
          "s": 71.12,
          "e": 71.672
        },
        {
          "w": "little",
          "s": 71.672,
          "e": 72.499
        },
        {
          "w": "one,”",
          "s": 72.499,
          "e": 73.188
        },
        {
          "w": "said",
          "s": 73.188,
          "e": 73.74
        },
        {
          "w": "Polaris,",
          "s": 73.74,
          "e": 74.843
        },
        {
          "w": "the",
          "s": 74.843,
          "e": 75.256
        },
        {
          "w": "great",
          "s": 75.256,
          "e": 75.946
        },
        {
          "w": "North",
          "s": 75.946,
          "e": 76.635
        },
        {
          "w": "Star,",
          "s": 76.635,
          "e": 77.325
        },
        {
          "w": "“you",
          "s": 77.325,
          "e": 77.876
        },
        {
          "w": "are",
          "s": 77.876,
          "e": 78.29
        },
        {
          "w": "far",
          "s": 78.29,
          "e": 78.704
        },
        {
          "w": "too",
          "s": 78.704,
          "e": 79.117
        },
        {
          "w": "small",
          "s": 79.117,
          "e": 79.807
        },
        {
          "w": "to",
          "s": 79.807,
          "e": 80.082
        },
        {
          "w": "be",
          "s": 80.082,
          "e": 80.358
        },
        {
          "w": "seen",
          "s": 80.358,
          "e": 80.91
        },
        {
          "w": "from",
          "s": 80.91,
          "e": 81.461
        },
        {
          "w": "the",
          "s": 81.461,
          "e": 81.875
        },
        {
          "w": "ground.",
          "s": 81.875,
          "e": 82.84
        }
      ]
    },
    {
      "text": "Your light is like a whisper compared to ours.",
      "side": "left",
      "start": 82.84,
      "end": 87.16,
      "image": "8_left.jpg",
      "words": [
        {
          "w": "Your",
          "s": 82.84,
          "e": 83.295
        },
        {
          "w": "light",
          "s": 83.295,
          "e": 83.863
        },
        {
          "w": "is",
          "s": 83.863,
          "e": 84.091
        },
        {
          "w": "like",
          "s": 84.091,
          "e": 84.545
        },
        {
          "w": "a",
          "s": 84.545,
          "e": 84.659
        },
        {
          "w": "whisper",
          "s": 84.659,
          "e": 85.455
        },
        {
          "w": "compared",
          "s": 85.455,
          "e": 86.364
        },
        {
          "w": "to",
          "s": 86.364,
          "e": 86.592
        },
        {
          "w": "ours.",
          "s": 86.592,
          "e": 87.16
        }
      ]
    },
    {
      "text": "You must wait until you grow bigger.”  Twink’s heart sank like a pebble in a pond.",
      "side": "right",
      "start": 87.16,
      "end": 94.2,
      "image": "9_right.jpg",
      "words": [
        {
          "w": "You",
          "s": 87.16,
          "e": 87.48
        },
        {
          "w": "must",
          "s": 87.48,
          "e": 87.907
        },
        {
          "w": "wait",
          "s": 87.907,
          "e": 88.333
        },
        {
          "w": "until",
          "s": 88.333,
          "e": 88.867
        },
        {
          "w": "you",
          "s": 88.867,
          "e": 89.187
        },
        {
          "w": "grow",
          "s": 89.187,
          "e": 89.613
        },
        {
          "w": "bigger.”",
          "s": 89.613,
          "e": 90.467
        },
        {
          "w": "Twink’s",
          "s": 90.467,
          "e": 91.213
        },
        {
          "w": "heart",
          "s": 91.213,
          "e": 91.747
        },
        {
          "w": "sank",
          "s": 91.747,
          "e": 92.173
        },
        {
          "w": "like",
          "s": 92.173,
          "e": 92.6
        },
        {
          "w": "a",
          "s": 92.6,
          "e": 92.707
        },
        {
          "w": "pebble",
          "s": 92.707,
          "e": 93.347
        },
        {
          "w": "in",
          "s": 93.347,
          "e": 93.56
        },
        {
          "w": "a",
          "s": 93.56,
          "e": 93.667
        },
        {
          "w": "pond.",
          "s": 93.667,
          "e": 94.2
        }
      ]
    },
    {
      "text": "She looked down at the world below, where children were hanging stockings by the fireplace and leaving out cookies for Santa.",
      "side": "left",
      "start": 94.2,
      "end": 102.88,
      "image": "10_left.jpg",
      "words": [
        {
          "w": "She",
          "s": 94.2,
          "e": 94.448
        },
        {
          "w": "looked",
          "s": 94.448,
          "e": 94.944
        },
        {
          "w": "down",
          "s": 94.944,
          "e": 95.275
        },
        {
          "w": "at",
          "s": 95.275,
          "e": 95.44
        },
        {
          "w": "the",
          "s": 95.44,
          "e": 95.688
        },
        {
          "w": "world",
          "s": 95.688,
          "e": 96.101
        },
        {
          "w": "below,",
          "s": 96.101,
          "e": 96.597
        },
        {
          "w": "where",
          "s": 96.597,
          "e": 97.011
        },
        {
          "w": "children",
          "s": 97.011,
          "e": 97.672
        },
        {
          "w": "were",
          "s": 97.672,
          "e": 98.003
        },
        {
          "w": "hanging",
          "s": 98.003,
          "e": 98.581
        },
        {
          "w": "stockings",
          "s": 98.581,
          "e": 99.325
        },
        {
          "w": "by",
          "s": 99.325,
          "e": 99.491
        },
        {
          "w": "the",
          "s": 99.491,
          "e": 99.739
        },
        {
          "w": "fireplace",
          "s": 99.739,
          "e": 100.483
        },
        {
          "w": "and",
          "s": 100.483,
          "e": 100.731
        },
        {
          "w": "leaving",
          "s": 100.731,
          "e": 101.309
        },
        {
          "w": "out",
          "s": 101.309,
          "e": 101.557
        },
        {
          "w": "cookies",
          "s": 101.557,
          "e": 102.136
        },
        {
          "w": "for",
          "s": 102.136,
          "e": 102.384
        },
        {
          "w": "Santa.",
          "s": 102.384,
          "e": 102.88
        }
      ]
    },
    {
      "text": "She so badly wanted to be part of the magic.",
      "side": "right",
      "start": 102.88,
      "end": 105.76,
      "image": "11_right.jpg",
      "words": [
        {
          "w": "She",
          "s": 102.88,
          "e": 103.127
        },
        {
          "w": "so",
          "s": 103.127,
          "e": 103.291
        },
        {
          "w": "badly",
          "s": 103.291,
          "e": 103.703
        },
        {
          "w": "wanted",
          "s": 103.703,
          "e": 104.197
        },
        {
          "w": "to",
          "s": 104.197,
          "e": 104.361
        },
        {
          "w": "be",
          "s": 104.361,
          "e": 104.526
        },
        {
          "w": "part",
          "s": 104.526,
          "e": 104.855
        },
        {
          "w": "of",
          "s": 104.855,
          "e": 105.019
        },
        {
          "w": "the",
          "s": 105.019,
          "e": 105.266
        },
        {
          "w": "magic.",
          "s": 105.266,
          "e": 105.76
        }
      ]
    },
    {
      "text": "“But what if I never grow big enough?” she worried.",
      "side": "left",
      "start": 105.76,
      "end": 110.28,
      "image": "12_left.jpg",
      "words": [
        {
          "w": "“But",
          "s": 105.76,
          "e": 106.19
        },
        {
          "w": "what",
          "s": 106.19,
          "e": 106.621
        },
        {
          "w": "if",
          "s": 106.621,
          "e": 106.836
        },
        {
          "w": "I",
          "s": 106.836,
          "e": 106.944
        },
        {
          "w": "never",
          "s": 106.944,
          "e": 107.482
        },
        {
          "w": "grow",
          "s": 107.482,
          "e": 107.912
        },
        {
          "w": "big",
          "s": 107.912,
          "e": 108.235
        },
        {
          "w": "enough?”",
          "s": 108.235,
          "e": 109.096
        },
        {
          "w": "she",
          "s": 109.096,
          "e": 109.419
        },
        {
          "w": "worried.",
          "s": 109.419,
          "e": 110.28
        }
      ]
    },
    {
      "text": "That night, as the other stars began their evening glow, Twink decided she wouldn’t give up.",
      "side": "right",
      "start": 110.28,
      "end": 117.4,
      "image": "13_right.jpg",
      "words": [
        {
          "w": "That",
          "s": 110.28,
          "e": 110.65
        },
        {
          "w": "night,",
          "s": 110.65,
          "e": 111.205
        },
        {
          "w": "as",
          "s": 111.205,
          "e": 111.39
        },
        {
          "w": "the",
          "s": 111.39,
          "e": 111.667
        },
        {
          "w": "other",
          "s": 111.667,
          "e": 112.129
        },
        {
          "w": "stars",
          "s": 112.129,
          "e": 112.592
        },
        {
          "w": "began",
          "s": 112.592,
          "e": 113.054
        },
        {
          "w": "their",
          "s": 113.054,
          "e": 113.516
        },
        {
          "w": "evening",
          "s": 113.516,
          "e": 114.164
        },
        {
          "w": "glow,",
          "s": 114.164,
          "e": 114.626
        },
        {
          "w": "Twink",
          "s": 114.626,
          "e": 115.088
        },
        {
          "w": "decided",
          "s": 115.088,
          "e": 115.736
        },
        {
          "w": "she",
          "s": 115.736,
          "e": 116.013
        },
        {
          "w": "wouldn’t",
          "s": 116.013,
          "e": 116.753
        },
        {
          "w": "give",
          "s": 116.753,
          "e": 117.123
        },
        {
          "w": "up.",
          "s": 117.123,
          "e": 117.4
        }
      ]
    },
    {
      "text": "She stretched her tiny rays as far as they could go, but no matter how hard she tried, her light barely reached the treetops.",
      "side": "left",
      "start": 117.4,
      "end": 125.96,
      "image": "14_left.jpg",
      "words": [
        {
          "w": "She",
          "s": 117.4,
          "e": 117.652
        },
        {
          "w": "stretched",
          "s": 117.652,
          "e": 118.407
        },
        {
          "w": "her",
          "s": 118.407,
          "e": 118.659
        },
        {
          "w": "tiny",
          "s": 118.659,
          "e": 118.995
        },
        {
          "w": "rays",
          "s": 118.995,
          "e": 119.33
        },
        {
          "w": "as",
          "s": 119.33,
          "e": 119.498
        },
        {
          "w": "far",
          "s": 119.498,
          "e": 119.75
        },
        {
          "w": "as",
          "s": 119.75,
          "e": 119.918
        },
        {
          "w": "they",
          "s": 119.918,
          "e": 120.253
        },
        {
          "w": "could",
          "s": 120.253,
          "e": 120.673
        },
        {
          "w": "go,",
          "s": 120.673,
          "e": 120.925
        },
        {
          "w": "but",
          "s": 120.925,
          "e": 121.176
        },
        {
          "w": "no",
          "s": 121.176,
          "e": 121.344
        },
        {
          "w": "matter",
          "s": 121.344,
          "e": 121.848
        },
        {
          "w": "how",
          "s": 121.848,
          "e": 122.1
        },
        {
          "w": "hard",
          "s": 122.1,
          "e": 122.435
        },
        {
          "w": "she",
          "s": 122.435,
          "e": 122.687
        },
        {
          "w": "tried,",
          "s": 122.687,
          "e": 123.191
        },
        {
          "w": "her",
          "s": 123.191,
          "e": 123.442
        },
        {
          "w": "light",
          "s": 123.442,
          "e": 123.862
        },
        {
          "w": "barely",
          "s": 123.862,
          "e": 124.365
        },
        {
          "w": "reached",
          "s": 124.365,
          "e": 124.953
        },
        {
          "w": "the",
          "s": 124.953,
          "e": 125.205
        },
        {
          "w": "treetops.",
          "s": 125.205,
          "e": 125.96
        }
      ]
    },
    {
      "text": "Just as she was about to sigh in disappointment, a soft voice floated up from the earth below.",
      "side": "right",
      "start": 125.96,
      "end": 132.52,
      "image": "15_right.jpg",
      "words": [
        {
          "w": "Just",
          "s": 125.96,
          "e": 126.301
        },
        {
          "w": "as",
          "s": 126.301,
          "e": 126.471
        },
        {
          "w": "she",
          "s": 126.471,
          "e": 126.727
        },
        {
          "w": "was",
          "s": 126.727,
          "e": 126.982
        },
        {
          "w": "about",
          "s": 126.982,
          "e": 127.408
        },
        {
          "w": "to",
          "s": 127.408,
          "e": 127.579
        },
        {
          "w": "sigh",
          "s": 127.579,
          "e": 127.919
        },
        {
          "w": "in",
          "s": 127.919,
          "e": 128.09
        },
        {
          "w": "disappointment,",
          "s": 128.09,
          "e": 129.368
        },
        {
          "w": "a",
          "s": 129.368,
          "e": 129.453
        },
        {
          "w": "soft",
          "s": 129.453,
          "e": 129.794
        },
        {
          "w": "voice",
          "s": 129.794,
          "e": 130.22
        },
        {
          "w": "floated",
          "s": 130.22,
          "e": 130.816
        },
        {
          "w": "up",
          "s": 130.816,
          "e": 130.986
        },
        {
          "w": "from",
          "s": 130.986,
          "e": 131.327
        },
        {
          "w": "the",
          "s": 131.327,
          "e": 131.583
        },
        {
          "w": "earth",
          "s": 131.583,
          "e": 132.009
        },
        {
          "w": "below.",
          "s": 132.009,
          "e": 132.52
        }
      ]
    },
    {
      "text": "“Hello, little star,” said the voice.",
      "side": "left",
      "start": 132.52,
      "end": 135.92,
      "image": "16_left.jpg",
      "words": [
        {
          "w": "“Hello,",
          "s": 132.52,
          "e": 133.264
        },
        {
          "w": "little",
          "s": 133.264,
          "e": 133.901
        },
        {
          "w": "star,”",
          "s": 133.901,
          "e": 134.539
        },
        {
          "w": "said",
          "s": 134.539,
          "e": 134.964
        },
        {
          "w": "the",
          "s": 134.964,
          "e": 135.282
        },
        {
          "w": "voice.",
          "s": 135.282,
          "e": 135.92
        }
      ]
    },
    {
      "text": "Twink peered down and saw a small girl named Lily, standing in her snowy backyard, her breath curling in the cold air.",
      "side": "right",
      "start": 135.92,
      "end": 145.0,
      "image": "17_right.jpg",
      "words": [
        {
          "w": "Twink",
          "s": 135.92,
          "e": 136.388
        },
        {
          "w": "peered",
          "s": 136.388,
          "e": 136.95
        },
        {
          "w": "down",
          "s": 136.95,
          "e": 137.324
        },
        {
          "w": "and",
          "s": 137.324,
          "e": 137.605
        },
        {
          "w": "saw",
          "s": 137.605,
          "e": 137.886
        },
        {
          "w": "a",
          "s": 137.886,
          "e": 137.979
        },
        {
          "w": "small",
          "s": 137.979,
          "e": 138.447
        },
        {
          "w": "girl",
          "s": 138.447,
          "e": 138.822
        },
        {
          "w": "named",
          "s": 138.822,
          "e": 139.29
        },
        {
          "w": "Lily,",
          "s": 139.29,
          "e": 139.758
        },
        {
          "w": "standing",
          "s": 139.758,
          "e": 140.507
        },
        {
          "w": "in",
          "s": 140.507,
          "e": 140.694
        },
        {
          "w": "her",
          "s": 140.694,
          "e": 140.975
        },
        {
          "w": "snowy",
          "s": 140.975,
          "e": 141.443
        },
        {
          "w": "backyard,",
          "s": 141.443,
          "e": 142.285
        },
        {
          "w": "her",
          "s": 142.285,
          "e": 142.566
        },
        {
          "w": "breath",
          "s": 142.566,
          "e": 143.128
        },
        {
          "w": "curling",
          "s": 143.128,
          "e": 143.783
        },
        {
          "w": "in",
          "s": 143.783,
          "e": 143.97
        },
        {
          "w": "the",
          "s": 143.97,
          "e": 144.251
        },
        {
          "w": "cold",
          "s": 144.251,
          "e": 144.626
        },
        {
          "w": "air.",
          "s": 144.626,
          "e": 145.0
        }
      ]
    },
    {
      "text": "Lily’s mittens were patched, and her coat was too thin for the winter chill, but her eyes sparkled with wonder.",
      "side": "left",
      "start": 145.0,
      "end": 151.88,
      "image": "18_left.jpg",
      "words": [
        {
          "w": "Lily’s",
          "s": 145.0,
          "e": 145.449
        },
        {
          "w": "mittens",
          "s": 145.449,
          "e": 145.972
        },
        {
          "w": "were",
          "s": 145.972,
          "e": 146.271
        },
        {
          "w": "patched,",
          "s": 146.271,
          "e": 146.87
        },
        {
          "w": "and",
          "s": 146.87,
          "e": 147.094
        },
        {
          "w": "her",
          "s": 147.094,
          "e": 147.318
        },
        {
          "w": "coat",
          "s": 147.318,
          "e": 147.617
        },
        {
          "w": "was",
          "s": 147.617,
          "e": 147.842
        },
        {
          "w": "too",
          "s": 147.842,
          "e": 148.066
        },
        {
          "w": "thin",
          "s": 148.066,
          "e": 148.365
        },
        {
          "w": "for",
          "s": 148.365,
          "e": 148.59
        },
        {
          "w": "the",
          "s": 148.59,
          "e": 148.814
        },
        {
          "w": "winter",
          "s": 148.814,
          "e": 149.263
        },
        {
          "w": "chill,",
          "s": 149.263,
          "e": 149.711
        },
        {
          "w": "but",
          "s": 149.711,
          "e": 149.936
        },
        {
          "w": "her",
          "s": 149.936,
          "e": 150.16
        },
        {
          "w": "eyes",
          "s": 150.16,
          "e": 150.459
        },
        {
          "w": "sparkled",
          "s": 150.459,
          "e": 151.057
        },
        {
          "w": "with",
          "s": 151.057,
          "e": 151.357
        },
        {
          "w": "wonder.",
          "s": 151.357,
          "e": 151.88
        }
      ]
    },
    {
      "text": "“I see you up there,” she whispered.",
      "side": "right",
      "start": 151.88,
      "end": 154.6,
      "image": "19_right.jpg",
      "words": [
        {
          "w": "“I",
          "s": 151.88,
          "e": 152.061
        },
        {
          "w": "see",
          "s": 152.061,
          "e": 152.333
        },
        {
          "w": "you",
          "s": 152.333,
          "e": 152.605
        },
        {
          "w": "up",
          "s": 152.605,
          "e": 152.787
        },
        {
          "w": "there,”",
          "s": 152.787,
          "e": 153.421
        },
        {
          "w": "she",
          "s": 153.421,
          "e": 153.693
        },
        {
          "w": "whispered.",
          "s": 153.693,
          "e": 154.6
        }
      ]
    },
    {
      "text": "“You’re the tiniest star, but you’re shining just for me, aren’t you?”  Twink’s heart leaped.",
      "side": "left",
      "start": 154.6,
      "end": 161.16,
      "image": "20_left.jpg",
      "words": [
        {
          "w": "“You’re",
          "s": 154.6,
          "e": 155.189
        },
        {
          "w": "the",
          "s": 155.189,
          "e": 155.441
        },
        {
          "w": "tiniest",
          "s": 155.441,
          "e": 156.03
        },
        {
          "w": "star,",
          "s": 156.03,
          "e": 156.45
        },
        {
          "w": "but",
          "s": 156.45,
          "e": 156.703
        },
        {
          "w": "you’re",
          "s": 156.703,
          "e": 157.207
        },
        {
          "w": "shining",
          "s": 157.207,
          "e": 157.796
        },
        {
          "w": "just",
          "s": 157.796,
          "e": 158.132
        },
        {
          "w": "for",
          "s": 158.132,
          "e": 158.385
        },
        {
          "w": "me,",
          "s": 158.385,
          "e": 158.637
        },
        {
          "w": "aren’t",
          "s": 158.637,
          "e": 159.142
        },
        {
          "w": "you?”",
          "s": 159.142,
          "e": 159.562
        },
        {
          "w": "Twink’s",
          "s": 159.562,
          "e": 160.151
        },
        {
          "w": "heart",
          "s": 160.151,
          "e": 160.571
        },
        {
          "w": "leaped.",
          "s": 160.571,
          "e": 161.16
        }
      ]
    },
    {
      "text": "“You can see me?” she asked, her light flickering with joy. “Of course I can,” said Lily.",
      "side": "right",
      "start": 161.16,
      "end": 169.4,
      "image": "21_right.jpg",
      "words": [
        {
          "w": "“You",
          "s": 161.16,
          "e": 161.612
        },
        {
          "w": "can",
          "s": 161.612,
          "e": 161.95
        },
        {
          "w": "see",
          "s": 161.95,
          "e": 162.289
        },
        {
          "w": "me?”",
          "s": 162.289,
          "e": 162.74
        },
        {
          "w": "she",
          "s": 162.74,
          "e": 163.079
        },
        {
          "w": "asked,",
          "s": 163.079,
          "e": 163.756
        },
        {
          "w": "her",
          "s": 163.756,
          "e": 164.095
        },
        {
          "w": "light",
          "s": 164.095,
          "e": 164.659
        },
        {
          "w": "flickering",
          "s": 164.659,
          "e": 165.788
        },
        {
          "w": "with",
          "s": 165.788,
          "e": 166.239
        },
        {
          "w": "joy.",
          "s": 166.239,
          "e": 166.691
        },
        {
          "w": "“Of",
          "s": 166.691,
          "e": 167.03
        },
        {
          "w": "course",
          "s": 167.03,
          "e": 167.707
        },
        {
          "w": "I",
          "s": 167.707,
          "e": 167.82
        },
        {
          "w": "can,”",
          "s": 167.82,
          "e": 168.384
        },
        {
          "w": "said",
          "s": 168.384,
          "e": 168.836
        },
        {
          "w": "Lily.",
          "s": 168.836,
          "e": 169.4
        }
      ]
    },
    {
      "text": "“You’re my special star. Every Christmas Eve, I look for you.",
      "side": "left",
      "start": 169.4,
      "end": 176.04,
      "image": "22_left.jpg",
      "words": [
        {
          "w": "“You’re",
          "s": 169.4,
          "e": 170.311
        },
        {
          "w": "my",
          "s": 170.311,
          "e": 170.572
        },
        {
          "w": "special",
          "s": 170.572,
          "e": 171.483
        },
        {
          "w": "star.",
          "s": 171.483,
          "e": 172.134
        },
        {
          "w": "Every",
          "s": 172.134,
          "e": 172.785
        },
        {
          "w": "Christmas",
          "s": 172.785,
          "e": 173.957
        },
        {
          "w": "Eve,",
          "s": 173.957,
          "e": 174.478
        },
        {
          "w": "I",
          "s": 174.478,
          "e": 174.608
        },
        {
          "w": "look",
          "s": 174.608,
          "e": 175.129
        },
        {
          "w": "for",
          "s": 175.129,
          "e": 175.519
        },
        {
          "w": "you.",
          "s": 175.519,
          "e": 176.04
        }
      ]
    },
    {
      "text": "The big stars are beautiful, but you’re the one that makes my heart feel warm.”  Twink’s glow grew brighter than it ever had before.",
      "side": "right",
      "start": 176.04,
      "end": 186.0,
      "image": "23_right.jpg",
      "words": [
        {
          "w": "The",
          "s": 176.04,
          "e": 176.317
        },
        {
          "w": "big",
          "s": 176.317,
          "e": 176.593
        },
        {
          "w": "stars",
          "s": 176.593,
          "e": 177.054
        },
        {
          "w": "are",
          "s": 177.054,
          "e": 177.331
        },
        {
          "w": "beautiful,",
          "s": 177.331,
          "e": 178.253
        },
        {
          "w": "but",
          "s": 178.253,
          "e": 178.53
        },
        {
          "w": "you’re",
          "s": 178.53,
          "e": 179.083
        },
        {
          "w": "the",
          "s": 179.083,
          "e": 179.36
        },
        {
          "w": "one",
          "s": 179.36,
          "e": 179.637
        },
        {
          "w": "that",
          "s": 179.637,
          "e": 180.006
        },
        {
          "w": "makes",
          "s": 180.006,
          "e": 180.467
        },
        {
          "w": "my",
          "s": 180.467,
          "e": 180.651
        },
        {
          "w": "heart",
          "s": 180.651,
          "e": 181.112
        },
        {
          "w": "feel",
          "s": 181.112,
          "e": 181.481
        },
        {
          "w": "warm.”",
          "s": 181.481,
          "e": 182.034
        },
        {
          "w": "Twink’s",
          "s": 182.034,
          "e": 182.68
        },
        {
          "w": "glow",
          "s": 182.68,
          "e": 183.049
        },
        {
          "w": "grew",
          "s": 183.049,
          "e": 183.418
        },
        {
          "w": "brighter",
          "s": 183.418,
          "e": 184.156
        },
        {
          "w": "than",
          "s": 184.156,
          "e": 184.524
        },
        {
          "w": "it",
          "s": 184.524,
          "e": 184.709
        },
        {
          "w": "ever",
          "s": 184.709,
          "e": 185.078
        },
        {
          "w": "had",
          "s": 185.078,
          "e": 185.354
        },
        {
          "w": "before.",
          "s": 185.354,
          "e": 186.0
        }
      ]
    },
    {
      "text": "She realized then that even the smallest light could make a difference to someone who needed it.",
      "side": "left",
      "start": 186.0,
      "end": 192.04,
      "image": "24_left.jpg",
      "words": [
        {
          "w": "She",
          "s": 186.0,
          "e": 186.226
        },
        {
          "w": "realized",
          "s": 186.226,
          "e": 186.83
        },
        {
          "w": "then",
          "s": 186.83,
          "e": 187.132
        },
        {
          "w": "that",
          "s": 187.132,
          "e": 187.434
        },
        {
          "w": "even",
          "s": 187.434,
          "e": 187.736
        },
        {
          "w": "the",
          "s": 187.736,
          "e": 187.963
        },
        {
          "w": "smallest",
          "s": 187.963,
          "e": 188.567
        },
        {
          "w": "light",
          "s": 188.567,
          "e": 188.944
        },
        {
          "w": "could",
          "s": 188.944,
          "e": 189.322
        },
        {
          "w": "make",
          "s": 189.322,
          "e": 189.624
        },
        {
          "w": "a",
          "s": 189.624,
          "e": 189.699
        },
        {
          "w": "difference",
          "s": 189.699,
          "e": 190.454
        },
        {
          "w": "to",
          "s": 190.454,
          "e": 190.605
        },
        {
          "w": "someone",
          "s": 190.605,
          "e": 191.134
        },
        {
          "w": "who",
          "s": 191.134,
          "e": 191.36
        },
        {
          "w": "needed",
          "s": 191.36,
          "e": 191.813
        },
        {
          "w": "it.",
          "s": 191.813,
          "e": 192.04
        }
      ]
    },
    {
      "text": "With renewed determination, she focused all her energy on shining as brightly as she could.",
      "side": "right",
      "start": 192.04,
      "end": 198.92,
      "image": "25_right.jpg",
      "words": [
        {
          "w": "With",
          "s": 192.04,
          "e": 192.397
        },
        {
          "w": "renewed",
          "s": 192.397,
          "e": 193.023
        },
        {
          "w": "determination,",
          "s": 193.023,
          "e": 194.274
        },
        {
          "w": "she",
          "s": 194.274,
          "e": 194.542
        },
        {
          "w": "focused",
          "s": 194.542,
          "e": 195.167
        },
        {
          "w": "all",
          "s": 195.167,
          "e": 195.435
        },
        {
          "w": "her",
          "s": 195.435,
          "e": 195.703
        },
        {
          "w": "energy",
          "s": 195.703,
          "e": 196.239
        },
        {
          "w": "on",
          "s": 196.239,
          "e": 196.418
        },
        {
          "w": "shining",
          "s": 196.418,
          "e": 197.044
        },
        {
          "w": "as",
          "s": 197.044,
          "e": 197.222
        },
        {
          "w": "brightly",
          "s": 197.222,
          "e": 197.937
        },
        {
          "w": "as",
          "s": 197.937,
          "e": 198.116
        },
        {
          "w": "she",
          "s": 198.116,
          "e": 198.384
        },
        {
          "w": "could.",
          "s": 198.384,
          "e": 198.92
        }
      ]
    },
    {
      "text": "Meanwhile, high above the earth, Santa Claus was preparing for his long journey.",
      "side": "left",
      "start": 198.92,
      "end": 205.4,
      "image": "26_left.jpg",
      "words": [
        {
          "w": "Meanwhile,",
          "s": 198.92,
          "e": 199.873
        },
        {
          "w": "high",
          "s": 199.873,
          "e": 200.254
        },
        {
          "w": "above",
          "s": 200.254,
          "e": 200.731
        },
        {
          "w": "the",
          "s": 200.731,
          "e": 201.016
        },
        {
          "w": "earth,",
          "s": 201.016,
          "e": 201.588
        },
        {
          "w": "Santa",
          "s": 201.588,
          "e": 202.065
        },
        {
          "w": "Claus",
          "s": 202.065,
          "e": 202.541
        },
        {
          "w": "was",
          "s": 202.541,
          "e": 202.827
        },
        {
          "w": "preparing",
          "s": 202.827,
          "e": 203.685
        },
        {
          "w": "for",
          "s": 203.685,
          "e": 203.971
        },
        {
          "w": "his",
          "s": 203.971,
          "e": 204.256
        },
        {
          "w": "long",
          "s": 204.256,
          "e": 204.638
        },
        {
          "w": "journey.",
          "s": 204.638,
          "e": 205.4
        }
      ]
    },
    {
      "text": "His sleigh was packed with presents, and his reindeer were prancing with excitement.",
      "side": "right",
      "start": 205.4,
      "end": 211.2,
      "image": "27_right.jpg",
      "words": [
        {
          "w": "His",
          "s": 205.4,
          "e": 205.642
        },
        {
          "w": "sleigh",
          "s": 205.642,
          "e": 206.125
        },
        {
          "w": "was",
          "s": 206.125,
          "e": 206.367
        },
        {
          "w": "packed",
          "s": 206.367,
          "e": 206.85
        },
        {
          "w": "with",
          "s": 206.85,
          "e": 207.172
        },
        {
          "w": "presents,",
          "s": 207.172,
          "e": 207.897
        },
        {
          "w": "and",
          "s": 207.897,
          "e": 208.139
        },
        {
          "w": "his",
          "s": 208.139,
          "e": 208.381
        },
        {
          "w": "reindeer",
          "s": 208.381,
          "e": 209.025
        },
        {
          "w": "were",
          "s": 209.025,
          "e": 209.347
        },
        {
          "w": "prancing",
          "s": 209.347,
          "e": 209.992
        },
        {
          "w": "with",
          "s": 209.992,
          "e": 210.314
        },
        {
          "w": "excitement.",
          "s": 210.314,
          "e": 211.2
        }
      ]
    },
    {
      "text": "But as he looked up at the sky, he frowned.",
      "side": "left",
      "start": 211.2,
      "end": 214.44,
      "image": "28_left.jpg",
      "words": [
        {
          "w": "But",
          "s": 211.2,
          "e": 211.486
        },
        {
          "w": "as",
          "s": 211.486,
          "e": 211.676
        },
        {
          "w": "he",
          "s": 211.676,
          "e": 211.867
        },
        {
          "w": "looked",
          "s": 211.867,
          "e": 212.439
        },
        {
          "w": "up",
          "s": 212.439,
          "e": 212.629
        },
        {
          "w": "at",
          "s": 212.629,
          "e": 212.82
        },
        {
          "w": "the",
          "s": 212.82,
          "e": 213.106
        },
        {
          "w": "sky,",
          "s": 213.106,
          "e": 213.487
        },
        {
          "w": "he",
          "s": 213.487,
          "e": 213.678
        },
        {
          "w": "frowned.",
          "s": 213.678,
          "e": 214.44
        }
      ]
    },
    {
      "text": "“Hmm,” he murmured, “there’s a gap in the starlight over Lily’s house.",
      "side": "right",
      "start": 214.44,
      "end": 221.16,
      "image": "29_right.jpg",
      "words": [
        {
          "w": "“Hmm,”",
          "s": 214.44,
          "e": 215.123
        },
        {
          "w": "he",
          "s": 215.123,
          "e": 215.351
        },
        {
          "w": "murmured,",
          "s": 215.351,
          "e": 216.376
        },
        {
          "w": "“there’s",
          "s": 216.376,
          "e": 217.287
        },
        {
          "w": "a",
          "s": 217.287,
          "e": 217.401
        },
        {
          "w": "gap",
          "s": 217.401,
          "e": 217.743
        },
        {
          "w": "in",
          "s": 217.743,
          "e": 217.971
        },
        {
          "w": "the",
          "s": 217.971,
          "e": 218.313
        },
        {
          "w": "starlight",
          "s": 218.313,
          "e": 219.338
        },
        {
          "w": "over",
          "s": 219.338,
          "e": 219.793
        },
        {
          "w": "Lily’s",
          "s": 219.793,
          "e": 220.477
        },
        {
          "w": "house.",
          "s": 220.477,
          "e": 221.16
        }
      ]
    },
    {
      "text": "The path isn’t as bright as it should be.”  Santa’s elves scurried about, checking their maps.",
      "side": "left",
      "start": 221.16,
      "end": 227.12,
      "image": "30_left.jpg",
      "words": [
        {
          "w": "The",
          "s": 221.16,
          "e": 221.389
        },
        {
          "w": "path",
          "s": 221.389,
          "e": 221.695
        },
        {
          "w": "isn’t",
          "s": 221.695,
          "e": 222.077
        },
        {
          "w": "as",
          "s": 222.077,
          "e": 222.23
        },
        {
          "w": "bright",
          "s": 222.23,
          "e": 222.688
        },
        {
          "w": "as",
          "s": 222.688,
          "e": 222.841
        },
        {
          "w": "it",
          "s": 222.841,
          "e": 222.994
        },
        {
          "w": "should",
          "s": 222.994,
          "e": 223.452
        },
        {
          "w": "be.”",
          "s": 223.452,
          "e": 223.758
        },
        {
          "w": "Santa’s",
          "s": 223.758,
          "e": 224.293
        },
        {
          "w": "elves",
          "s": 224.293,
          "e": 224.675
        },
        {
          "w": "scurried",
          "s": 224.675,
          "e": 225.286
        },
        {
          "w": "about,",
          "s": 225.286,
          "e": 225.745
        },
        {
          "w": "checking",
          "s": 225.745,
          "e": 226.356
        },
        {
          "w": "their",
          "s": 226.356,
          "e": 226.738
        },
        {
          "w": "maps.",
          "s": 226.738,
          "e": 227.12
        }
      ]
    },
    {
      "text": "“The stars are all in their proper places, sir,” said one.",
      "side": "right",
      "start": 227.12,
      "end": 231.96,
      "image": "31_right.jpg",
      "words": [
        {
          "w": "“The",
          "s": 227.12,
          "e": 227.523
        },
        {
          "w": "stars",
          "s": 227.523,
          "e": 228.028
        },
        {
          "w": "are",
          "s": 228.028,
          "e": 228.33
        },
        {
          "w": "all",
          "s": 228.33,
          "e": 228.633
        },
        {
          "w": "in",
          "s": 228.633,
          "e": 228.834
        },
        {
          "w": "their",
          "s": 228.834,
          "e": 229.338
        },
        {
          "w": "proper",
          "s": 229.338,
          "e": 229.943
        },
        {
          "w": "places,",
          "s": 229.943,
          "e": 230.649
        },
        {
          "w": "sir,”",
          "s": 230.649,
          "e": 231.153
        },
        {
          "w": "said",
          "s": 231.153,
          "e": 231.557
        },
        {
          "w": "one.",
          "s": 231.557,
          "e": 231.96
        }
      ]
    },
    {
      "text": "“There shouldn’t be a gap.”  But Santa knew better.",
      "side": "left",
      "start": 231.96,
      "end": 236.4,
      "image": "32_left.jpg",
      "words": [
        {
          "w": "“There",
          "s": 231.96,
          "e": 232.594
        },
        {
          "w": "shouldn’t",
          "s": 232.594,
          "e": 233.546
        },
        {
          "w": "be",
          "s": 233.546,
          "e": 233.757
        },
        {
          "w": "a",
          "s": 233.757,
          "e": 233.863
        },
        {
          "w": "gap.”",
          "s": 233.863,
          "e": 234.391
        },
        {
          "w": "But",
          "s": 234.391,
          "e": 234.709
        },
        {
          "w": "Santa",
          "s": 234.709,
          "e": 235.237
        },
        {
          "w": "knew",
          "s": 235.237,
          "e": 235.66
        },
        {
          "w": "better.",
          "s": 235.66,
          "e": 236.4
        }
      ]
    },
    {
      "text": "He had been delivering presents for centuries, and he knew that sometimes, the most important lights were the ones that weren’t supposed to be there.",
      "side": "right",
      "start": 236.4,
      "end": 245.16,
      "image": "33_right.jpg",
      "words": [
        {
          "w": "He",
          "s": 236.4,
          "e": 236.54
        },
        {
          "w": "had",
          "s": 236.54,
          "e": 236.75
        },
        {
          "w": "been",
          "s": 236.75,
          "e": 237.031
        },
        {
          "w": "delivering",
          "s": 237.031,
          "e": 237.732
        },
        {
          "w": "presents",
          "s": 237.732,
          "e": 238.292
        },
        {
          "w": "for",
          "s": 238.292,
          "e": 238.502
        },
        {
          "w": "centuries,",
          "s": 238.502,
          "e": 239.203
        },
        {
          "w": "and",
          "s": 239.203,
          "e": 239.413
        },
        {
          "w": "he",
          "s": 239.413,
          "e": 239.554
        },
        {
          "w": "knew",
          "s": 239.554,
          "e": 239.834
        },
        {
          "w": "that",
          "s": 239.834,
          "e": 240.114
        },
        {
          "w": "sometimes,",
          "s": 240.114,
          "e": 240.815
        },
        {
          "w": "the",
          "s": 240.815,
          "e": 241.025
        },
        {
          "w": "most",
          "s": 241.025,
          "e": 241.306
        },
        {
          "w": "important",
          "s": 241.306,
          "e": 241.936
        },
        {
          "w": "lights",
          "s": 241.936,
          "e": 242.357
        },
        {
          "w": "were",
          "s": 242.357,
          "e": 242.637
        },
        {
          "w": "the",
          "s": 242.637,
          "e": 242.847
        },
        {
          "w": "ones",
          "s": 242.847,
          "e": 243.128
        },
        {
          "w": "that",
          "s": 243.128,
          "e": 243.408
        },
        {
          "w": "weren’t",
          "s": 243.408,
          "e": 243.899
        },
        {
          "w": "supposed",
          "s": 243.899,
          "e": 244.459
        },
        {
          "w": "to",
          "s": 244.459,
          "e": 244.599
        },
        {
          "w": "be",
          "s": 244.599,
          "e": 244.74
        },
        {
          "w": "there.",
          "s": 244.74,
          "e": 245.16
        }
      ]
    },
    {
      "text": "“I think I know what’s missing,” he said with a twinkle in his eye.",
      "side": "left",
      "start": 245.16,
      "end": 250.64,
      "image": "34_left.jpg",
      "words": [
        {
          "w": "“I",
          "s": 245.16,
          "e": 245.363
        },
        {
          "w": "think",
          "s": 245.363,
          "e": 245.87
        },
        {
          "w": "I",
          "s": 245.87,
          "e": 245.972
        },
        {
          "w": "know",
          "s": 245.972,
          "e": 246.378
        },
        {
          "w": "what’s",
          "s": 246.378,
          "e": 246.987
        },
        {
          "w": "missing,”",
          "s": 246.987,
          "e": 247.9
        },
        {
          "w": "he",
          "s": 247.9,
          "e": 248.103
        },
        {
          "w": "said",
          "s": 248.103,
          "e": 248.509
        },
        {
          "w": "with",
          "s": 248.509,
          "e": 248.915
        },
        {
          "w": "a",
          "s": 248.915,
          "e": 249.016
        },
        {
          "w": "twinkle",
          "s": 249.016,
          "e": 249.727
        },
        {
          "w": "in",
          "s": 249.727,
          "e": 249.93
        },
        {
          "w": "his",
          "s": 249.93,
          "e": 250.234
        },
        {
          "w": "eye.",
          "s": 250.234,
          "e": 250.64
        }
      ]
    },
    {
      "text": "He reached into his sack and pulled out a tiny, shimmering thread of stardust.",
      "side": "right",
      "start": 250.64,
      "end": 255.6,
      "image": "35_right.jpg",
      "words": [
        {
          "w": "He",
          "s": 250.64,
          "e": 250.793
        },
        {
          "w": "reached",
          "s": 250.793,
          "e": 251.327
        },
        {
          "w": "into",
          "s": 251.327,
          "e": 251.632
        },
        {
          "w": "his",
          "s": 251.632,
          "e": 251.861
        },
        {
          "w": "sack",
          "s": 251.861,
          "e": 252.166
        },
        {
          "w": "and",
          "s": 252.166,
          "e": 252.395
        },
        {
          "w": "pulled",
          "s": 252.395,
          "e": 252.853
        },
        {
          "w": "out",
          "s": 252.853,
          "e": 253.082
        },
        {
          "w": "a",
          "s": 253.082,
          "e": 253.158
        },
        {
          "w": "tiny,",
          "s": 253.158,
          "e": 253.54
        },
        {
          "w": "shimmering",
          "s": 253.54,
          "e": 254.303
        },
        {
          "w": "thread",
          "s": 254.303,
          "e": 254.761
        },
        {
          "w": "of",
          "s": 254.761,
          "e": 254.913
        },
        {
          "w": "stardust.",
          "s": 254.913,
          "e": 255.6
        }
      ]
    },
    {
      "text": "“This should do the trick,” he said, tossing it into the sky.",
      "side": "left",
      "start": 255.6,
      "end": 260.48,
      "image": "36_left.jpg",
      "words": [
        {
          "w": "“This",
          "s": 255.6,
          "e": 256.088
        },
        {
          "w": "should",
          "s": 256.088,
          "e": 256.674
        },
        {
          "w": "do",
          "s": 256.674,
          "e": 256.869
        },
        {
          "w": "the",
          "s": 256.869,
          "e": 257.162
        },
        {
          "w": "trick,”",
          "s": 257.162,
          "e": 257.845
        },
        {
          "w": "he",
          "s": 257.845,
          "e": 258.04
        },
        {
          "w": "said,",
          "s": 258.04,
          "e": 258.528
        },
        {
          "w": "tossing",
          "s": 258.528,
          "e": 259.211
        },
        {
          "w": "it",
          "s": 259.211,
          "e": 259.406
        },
        {
          "w": "into",
          "s": 259.406,
          "e": 259.797
        },
        {
          "w": "the",
          "s": 259.797,
          "e": 260.09
        },
        {
          "w": "sky.",
          "s": 260.09,
          "e": 260.48
        }
      ]
    },
    {
      "text": "The stardust swirled and danced, wrapping itself around Twink.",
      "side": "right",
      "start": 260.48,
      "end": 265.64,
      "image": "37_right.jpg",
      "words": [
        {
          "w": "The",
          "s": 260.48,
          "e": 260.767
        },
        {
          "w": "stardust",
          "s": 260.767,
          "e": 261.531
        },
        {
          "w": "swirled",
          "s": 261.531,
          "e": 262.2
        },
        {
          "w": "and",
          "s": 262.2,
          "e": 262.487
        },
        {
          "w": "danced,",
          "s": 262.487,
          "e": 263.156
        },
        {
          "w": "wrapping",
          "s": 263.156,
          "e": 263.92
        },
        {
          "w": "itself",
          "s": 263.92,
          "e": 264.493
        },
        {
          "w": "around",
          "s": 264.493,
          "e": 265.067
        },
        {
          "w": "Twink.",
          "s": 265.067,
          "e": 265.64
        }
      ]
    },
    {
      "text": "Suddenly, her light grew stronger, brighter, and more beautiful than ever before.",
      "side": "left",
      "start": 265.64,
      "end": 271.8,
      "image": "38_left.jpg",
      "words": [
        {
          "w": "Suddenly,",
          "s": 265.64,
          "e": 266.432
        },
        {
          "w": "her",
          "s": 266.432,
          "e": 266.696
        },
        {
          "w": "light",
          "s": 266.696,
          "e": 267.136
        },
        {
          "w": "grew",
          "s": 267.136,
          "e": 267.488
        },
        {
          "w": "stronger,",
          "s": 267.488,
          "e": 268.28
        },
        {
          "w": "brighter,",
          "s": 268.28,
          "e": 269.072
        },
        {
          "w": "and",
          "s": 269.072,
          "e": 269.336
        },
        {
          "w": "more",
          "s": 269.336,
          "e": 269.688
        },
        {
          "w": "beautiful",
          "s": 269.688,
          "e": 270.48
        },
        {
          "w": "than",
          "s": 270.48,
          "e": 270.832
        },
        {
          "w": "ever",
          "s": 270.832,
          "e": 271.184
        },
        {
          "w": "before.",
          "s": 271.184,
          "e": 271.8
        }
      ]
    },
    {
      "text": "She wasn’t just a tiny star anymore—she was a beacon of hope, shining directly over Lily’s house.",
      "side": "right",
      "start": 271.8,
      "end": 279.72,
      "image": "39_right.jpg",
      "words": [
        {
          "w": "She",
          "s": 271.8,
          "e": 272.093
        },
        {
          "w": "wasn’t",
          "s": 272.093,
          "e": 272.68
        },
        {
          "w": "just",
          "s": 272.68,
          "e": 273.071
        },
        {
          "w": "a",
          "s": 273.071,
          "e": 273.169
        },
        {
          "w": "tiny",
          "s": 273.169,
          "e": 273.56
        },
        {
          "w": "star",
          "s": 273.56,
          "e": 273.951
        },
        {
          "w": "anymore—she",
          "s": 273.951,
          "e": 275.027
        },
        {
          "w": "was",
          "s": 275.027,
          "e": 275.32
        },
        {
          "w": "a",
          "s": 275.32,
          "e": 275.418
        },
        {
          "w": "beacon",
          "s": 275.418,
          "e": 276.004
        },
        {
          "w": "of",
          "s": 276.004,
          "e": 276.2
        },
        {
          "w": "hope,",
          "s": 276.2,
          "e": 276.689
        },
        {
          "w": "shining",
          "s": 276.689,
          "e": 277.373
        },
        {
          "w": "directly",
          "s": 277.373,
          "e": 278.156
        },
        {
          "w": "over",
          "s": 278.156,
          "e": 278.547
        },
        {
          "w": "Lily’s",
          "s": 278.547,
          "e": 279.133
        },
        {
          "w": "house.",
          "s": 279.133,
          "e": 279.72
        }
      ]
    },
    {
      "text": "Down below, Lily gasped. “Look, Mama!” she cried, pointing at the sky.",
      "side": "left",
      "start": 279.72,
      "end": 286.44,
      "image": "40_left.jpg",
      "words": [
        {
          "w": "Down",
          "s": 279.72,
          "e": 280.176
        },
        {
          "w": "below,",
          "s": 280.176,
          "e": 280.859
        },
        {
          "w": "Lily",
          "s": 280.859,
          "e": 281.315
        },
        {
          "w": "gasped.",
          "s": 281.315,
          "e": 282.112
        },
        {
          "w": "“Look,",
          "s": 282.112,
          "e": 282.795
        },
        {
          "w": "Mama!”",
          "s": 282.795,
          "e": 283.479
        },
        {
          "w": "she",
          "s": 283.479,
          "e": 283.82
        },
        {
          "w": "cried,",
          "s": 283.82,
          "e": 284.504
        },
        {
          "w": "pointing",
          "s": 284.504,
          "e": 285.415
        },
        {
          "w": "at",
          "s": 285.415,
          "e": 285.643
        },
        {
          "w": "the",
          "s": 285.643,
          "e": 285.984
        },
        {
          "w": "sky.",
          "s": 285.984,
          "e": 286.44
        }
      ]
    },
    {
      "text": "“My little star is the brightest one of all tonight!”  Her mother smiled and wrapped a warm blanket around her shoulders.",
      "side": "right",
      "start": 286.44,
      "end": 295.4,
      "image": "41_right.jpg",
      "words": [
        {
          "w": "“My",
          "s": 286.44,
          "e": 286.709
        },
        {
          "w": "little",
          "s": 286.709,
          "e": 287.246
        },
        {
          "w": "star",
          "s": 287.246,
          "e": 287.605
        },
        {
          "w": "is",
          "s": 287.605,
          "e": 287.784
        },
        {
          "w": "the",
          "s": 287.784,
          "e": 288.053
        },
        {
          "w": "brightest",
          "s": 288.053,
          "e": 288.859
        },
        {
          "w": "one",
          "s": 288.859,
          "e": 289.128
        },
        {
          "w": "of",
          "s": 289.128,
          "e": 289.307
        },
        {
          "w": "all",
          "s": 289.307,
          "e": 289.576
        },
        {
          "w": "tonight!”",
          "s": 289.576,
          "e": 290.382
        },
        {
          "w": "Her",
          "s": 290.382,
          "e": 290.651
        },
        {
          "w": "mother",
          "s": 290.651,
          "e": 291.189
        },
        {
          "w": "smiled",
          "s": 291.189,
          "e": 291.726
        },
        {
          "w": "and",
          "s": 291.726,
          "e": 291.995
        },
        {
          "w": "wrapped",
          "s": 291.995,
          "e": 292.622
        },
        {
          "w": "a",
          "s": 292.622,
          "e": 292.712
        },
        {
          "w": "warm",
          "s": 292.712,
          "e": 293.07
        },
        {
          "w": "blanket",
          "s": 293.07,
          "e": 293.698
        },
        {
          "w": "around",
          "s": 293.698,
          "e": 294.235
        },
        {
          "w": "her",
          "s": 294.235,
          "e": 294.504
        },
        {
          "w": "shoulders.",
          "s": 294.504,
          "e": 295.4
        }
      ]
    },
    {
      "text": "“That’s because it’s shining just for you, my dear.”  And so, as Santa’s sleigh soared through the night, Twink guided him safely to Lily’s house.",
      "side": "left",
      "start": 295.4,
      "end": 306.2,
      "image": "42_left.jpg",
      "words": [
        {
          "w": "“That’s",
          "s": 295.4,
          "e": 296.025
        },
        {
          "w": "because",
          "s": 296.025,
          "e": 296.65
        },
        {
          "w": "it’s",
          "s": 296.65,
          "e": 297.007
        },
        {
          "w": "shining",
          "s": 297.007,
          "e": 297.631
        },
        {
          "w": "just",
          "s": 297.631,
          "e": 297.988
        },
        {
          "w": "for",
          "s": 297.988,
          "e": 298.256
        },
        {
          "w": "you,",
          "s": 298.256,
          "e": 298.613
        },
        {
          "w": "my",
          "s": 298.613,
          "e": 298.792
        },
        {
          "w": "dear.”",
          "s": 298.792,
          "e": 299.327
        },
        {
          "w": "And",
          "s": 299.327,
          "e": 299.595
        },
        {
          "w": "so,",
          "s": 299.595,
          "e": 299.863
        },
        {
          "w": "as",
          "s": 299.863,
          "e": 300.041
        },
        {
          "w": "Santa’s",
          "s": 300.041,
          "e": 300.666
        },
        {
          "w": "sleigh",
          "s": 300.666,
          "e": 301.202
        },
        {
          "w": "soared",
          "s": 301.202,
          "e": 301.737
        },
        {
          "w": "through",
          "s": 301.737,
          "e": 302.362
        },
        {
          "w": "the",
          "s": 302.362,
          "e": 302.63
        },
        {
          "w": "night,",
          "s": 302.63,
          "e": 303.165
        },
        {
          "w": "Twink",
          "s": 303.165,
          "e": 303.612
        },
        {
          "w": "guided",
          "s": 303.612,
          "e": 304.147
        },
        {
          "w": "him",
          "s": 304.147,
          "e": 304.415
        },
        {
          "w": "safely",
          "s": 304.415,
          "e": 304.95
        },
        {
          "w": "to",
          "s": 304.95,
          "e": 305.129
        },
        {
          "w": "Lily’s",
          "s": 305.129,
          "e": 305.664
        },
        {
          "w": "house.",
          "s": 305.664,
          "e": 306.2
        }
      ]
    },
    {
      "text": "Her light was so warm and welcoming that Santa couldn’t help but stop.",
      "side": "right",
      "start": 306.2,
      "end": 310.6,
      "image": "43_right.jpg",
      "words": [
        {
          "w": "Her",
          "s": 306.2,
          "e": 306.428
        },
        {
          "w": "light",
          "s": 306.428,
          "e": 306.807
        },
        {
          "w": "was",
          "s": 306.807,
          "e": 307.034
        },
        {
          "w": "so",
          "s": 307.034,
          "e": 307.186
        },
        {
          "w": "warm",
          "s": 307.186,
          "e": 307.49
        },
        {
          "w": "and",
          "s": 307.49,
          "e": 307.717
        },
        {
          "w": "welcoming",
          "s": 307.717,
          "e": 308.4
        },
        {
          "w": "that",
          "s": 308.4,
          "e": 308.703
        },
        {
          "w": "Santa",
          "s": 308.703,
          "e": 309.083
        },
        {
          "w": "couldn’t",
          "s": 309.083,
          "e": 309.69
        },
        {
          "w": "help",
          "s": 309.69,
          "e": 309.993
        },
        {
          "w": "but",
          "s": 309.993,
          "e": 310.221
        },
        {
          "w": "stop.",
          "s": 310.221,
          "e": 310.6
        }
      ]
    },
    {
      "text": "He left an extra-special gift under the tree—a new coat, just the right size for Lily, with mittens that matched.",
      "side": "left",
      "start": 310.6,
      "end": 319.48,
      "image": "44_left.jpg",
      "words": [
        {
          "w": "He",
          "s": 310.6,
          "e": 310.789
        },
        {
          "w": "left",
          "s": 310.789,
          "e": 311.167
        },
        {
          "w": "an",
          "s": 311.167,
          "e": 311.356
        },
        {
          "w": "extra-special",
          "s": 311.356,
          "e": 312.584
        },
        {
          "w": "gift",
          "s": 312.584,
          "e": 312.962
        },
        {
          "w": "under",
          "s": 312.962,
          "e": 313.434
        },
        {
          "w": "the",
          "s": 313.434,
          "e": 313.717
        },
        {
          "w": "tree—a",
          "s": 313.717,
          "e": 314.284
        },
        {
          "w": "new",
          "s": 314.284,
          "e": 314.568
        },
        {
          "w": "coat,",
          "s": 314.568,
          "e": 315.04
        },
        {
          "w": "just",
          "s": 315.04,
          "e": 315.418
        },
        {
          "w": "the",
          "s": 315.418,
          "e": 315.701
        },
        {
          "w": "right",
          "s": 315.701,
          "e": 316.174
        },
        {
          "w": "size",
          "s": 316.174,
          "e": 316.551
        },
        {
          "w": "for",
          "s": 316.551,
          "e": 316.835
        },
        {
          "w": "Lily,",
          "s": 316.835,
          "e": 317.307
        },
        {
          "w": "with",
          "s": 317.307,
          "e": 317.685
        },
        {
          "w": "mittens",
          "s": 317.685,
          "e": 318.346
        },
        {
          "w": "that",
          "s": 318.346,
          "e": 318.724
        },
        {
          "w": "matched.",
          "s": 318.724,
          "e": 319.48
        }
      ]
    },
    {
      "text": "And as he flew away, he winked up at Twink. “Thank you, little star,” he said.",
      "side": "right",
      "start": 319.48,
      "end": 325.44,
      "image": "45_right.jpg",
      "words": [
        {
          "w": "And",
          "s": 319.48,
          "e": 319.764
        },
        {
          "w": "as",
          "s": 319.764,
          "e": 319.953
        },
        {
          "w": "he",
          "s": 319.953,
          "e": 320.142
        },
        {
          "w": "flew",
          "s": 320.142,
          "e": 320.521
        },
        {
          "w": "away,",
          "s": 320.521,
          "e": 320.994
        },
        {
          "w": "he",
          "s": 320.994,
          "e": 321.183
        },
        {
          "w": "winked",
          "s": 321.183,
          "e": 321.75
        },
        {
          "w": "up",
          "s": 321.75,
          "e": 321.94
        },
        {
          "w": "at",
          "s": 321.94,
          "e": 322.129
        },
        {
          "w": "Twink.",
          "s": 322.129,
          "e": 322.697
        },
        {
          "w": "“Thank",
          "s": 322.697,
          "e": 323.264
        },
        {
          "w": "you,",
          "s": 323.264,
          "e": 323.643
        },
        {
          "w": "little",
          "s": 323.643,
          "e": 324.21
        },
        {
          "w": "star,”",
          "s": 324.21,
          "e": 324.778
        },
        {
          "w": "he",
          "s": 324.778,
          "e": 324.967
        },
        {
          "w": "said.",
          "s": 324.967,
          "e": 325.44
        }
      ]
    },
    {
      "text": "“You made this Christmas Eve truly magical.”  From that night on, Twink knew that she didn’t need to be the biggest or the brightest star in the sky.",
      "side": "left",
      "start": 325.44,
      "end": 336.2,
      "image": "46_left.jpg",
      "words": [
        {
          "w": "“You",
          "s": 325.44,
          "e": 325.796
        },
        {
          "w": "made",
          "s": 325.796,
          "e": 326.151
        },
        {
          "w": "this",
          "s": 326.151,
          "e": 326.507
        },
        {
          "w": "Christmas",
          "s": 326.507,
          "e": 327.307
        },
        {
          "w": "Eve",
          "s": 327.307,
          "e": 327.574
        },
        {
          "w": "truly",
          "s": 327.574,
          "e": 328.019
        },
        {
          "w": "magical.”",
          "s": 328.019,
          "e": 328.819
        },
        {
          "w": "From",
          "s": 328.819,
          "e": 329.175
        },
        {
          "w": "that",
          "s": 329.175,
          "e": 329.531
        },
        {
          "w": "night",
          "s": 329.531,
          "e": 329.975
        },
        {
          "w": "on,",
          "s": 329.975,
          "e": 330.242
        },
        {
          "w": "Twink",
          "s": 330.242,
          "e": 330.687
        },
        {
          "w": "knew",
          "s": 330.687,
          "e": 331.042
        },
        {
          "w": "that",
          "s": 331.042,
          "e": 331.398
        },
        {
          "w": "she",
          "s": 331.398,
          "e": 331.665
        },
        {
          "w": "didn’t",
          "s": 331.665,
          "e": 332.198
        },
        {
          "w": "need",
          "s": 332.198,
          "e": 332.554
        },
        {
          "w": "to",
          "s": 332.554,
          "e": 332.732
        },
        {
          "w": "be",
          "s": 332.732,
          "e": 332.91
        },
        {
          "w": "the",
          "s": 332.91,
          "e": 333.177
        },
        {
          "w": "biggest",
          "s": 333.177,
          "e": 333.799
        },
        {
          "w": "or",
          "s": 333.799,
          "e": 333.977
        },
        {
          "w": "the",
          "s": 333.977,
          "e": 334.244
        },
        {
          "w": "brightest",
          "s": 334.244,
          "e": 335.044
        },
        {
          "w": "star",
          "s": 335.044,
          "e": 335.4
        },
        {
          "w": "in",
          "s": 335.4,
          "e": 335.578
        },
        {
          "w": "the",
          "s": 335.578,
          "e": 335.844
        },
        {
          "w": "sky.",
          "s": 335.844,
          "e": 336.2
        }
      ]
    },
    {
      "text": "She just needed to shine her light where it mattered most.",
      "side": "right",
      "start": 336.2,
      "end": 339.88,
      "image": "47_right.jpg",
      "words": [
        {
          "w": "She",
          "s": 336.2,
          "e": 336.43
        },
        {
          "w": "just",
          "s": 336.43,
          "e": 336.737
        },
        {
          "w": "needed",
          "s": 336.737,
          "e": 337.197
        },
        {
          "w": "to",
          "s": 337.197,
          "e": 337.35
        },
        {
          "w": "shine",
          "s": 337.35,
          "e": 337.733
        },
        {
          "w": "her",
          "s": 337.733,
          "e": 337.963
        },
        {
          "w": "light",
          "s": 337.963,
          "e": 338.347
        },
        {
          "w": "where",
          "s": 338.347,
          "e": 338.73
        },
        {
          "w": "it",
          "s": 338.73,
          "e": 338.883
        },
        {
          "w": "mattered",
          "s": 338.883,
          "e": 339.497
        },
        {
          "w": "most.",
          "s": 339.497,
          "e": 339.88
        }
      ]
    },
    {
      "text": "And every Christmas Eve after that, children all over the world would look up and smile when they saw the tiniest star shining just a little bit brighter than the rest.",
      "side": "left",
      "start": 339.88,
      "end": 350.6,
      "image": "48_left.jpg",
      "words": [
        {
          "w": "And",
          "s": 339.88,
          "e": 340.113
        },
        {
          "w": "every",
          "s": 340.113,
          "e": 340.501
        },
        {
          "w": "Christmas",
          "s": 340.501,
          "e": 341.201
        },
        {
          "w": "Eve",
          "s": 341.201,
          "e": 341.434
        },
        {
          "w": "after",
          "s": 341.434,
          "e": 341.822
        },
        {
          "w": "that,",
          "s": 341.822,
          "e": 342.21
        },
        {
          "w": "children",
          "s": 342.21,
          "e": 342.832
        },
        {
          "w": "all",
          "s": 342.832,
          "e": 343.065
        },
        {
          "w": "over",
          "s": 343.065,
          "e": 343.376
        },
        {
          "w": "the",
          "s": 343.376,
          "e": 343.609
        },
        {
          "w": "world",
          "s": 343.609,
          "e": 343.997
        },
        {
          "w": "would",
          "s": 343.997,
          "e": 344.386
        },
        {
          "w": "look",
          "s": 344.386,
          "e": 344.696
        },
        {
          "w": "up",
          "s": 344.696,
          "e": 344.852
        },
        {
          "w": "and",
          "s": 344.852,
          "e": 345.085
        },
        {
          "w": "smile",
          "s": 345.085,
          "e": 345.473
        },
        {
          "w": "when",
          "s": 345.473,
          "e": 345.784
        },
        {
          "w": "they",
          "s": 345.784,
          "e": 346.094
        },
        {
          "w": "saw",
          "s": 346.094,
          "e": 346.328
        },
        {
          "w": "the",
          "s": 346.328,
          "e": 346.561
        },
        {
          "w": "tiniest",
          "s": 346.561,
          "e": 347.104
        },
        {
          "w": "star",
          "s": 347.104,
          "e": 347.415
        },
        {
          "w": "shining",
          "s": 347.415,
          "e": 347.959
        },
        {
          "w": "just",
          "s": 347.959,
          "e": 348.27
        },
        {
          "w": "a",
          "s": 348.27,
          "e": 348.347
        },
        {
          "w": "little",
          "s": 348.347,
          "e": 348.813
        },
        {
          "w": "bit",
          "s": 348.813,
          "e": 349.046
        },
        {
          "w": "brighter",
          "s": 349.046,
          "e": 349.668
        },
        {
          "w": "than",
          "s": 349.668,
          "e": 349.979
        },
        {
          "w": "the",
          "s": 349.979,
          "e": 350.212
        },
        {
          "w": "rest.",
          "s": 350.212,
          "e": 350.6
        }
      ]
    },
    {
      "text": "And so, my dear, if you ever look up at the sky on Christmas Eve and see a tiny star winking at you, you’ll know it’s Twink, reminding you that even the smallest light can make the biggest difference.",
      "side": "right",
      "start": 350.6,
      "end": 366.4,
      "image": "49_right.jpg",
      "words": [
        {
          "w": "And",
          "s": 350.6,
          "e": 350.893
        },
        {
          "w": "so,",
          "s": 350.893,
          "e": 351.185
        },
        {
          "w": "my",
          "s": 351.185,
          "e": 351.38
        },
        {
          "w": "dear,",
          "s": 351.38,
          "e": 351.868
        },
        {
          "w": "if",
          "s": 351.868,
          "e": 352.063
        },
        {
          "w": "you",
          "s": 352.063,
          "e": 352.356
        },
        {
          "w": "ever",
          "s": 352.356,
          "e": 352.746
        },
        {
          "w": "look",
          "s": 352.746,
          "e": 353.136
        },
        {
          "w": "up",
          "s": 353.136,
          "e": 353.331
        },
        {
          "w": "at",
          "s": 353.331,
          "e": 353.526
        },
        {
          "w": "the",
          "s": 353.526,
          "e": 353.819
        },
        {
          "w": "sky",
          "s": 353.819,
          "e": 354.111
        },
        {
          "w": "on",
          "s": 354.111,
          "e": 354.306
        },
        {
          "w": "Christmas",
          "s": 354.306,
          "e": 355.184
        },
        {
          "w": "Eve",
          "s": 355.184,
          "e": 355.477
        },
        {
          "w": "and",
          "s": 355.477,
          "e": 355.769
        },
        {
          "w": "see",
          "s": 355.769,
          "e": 356.062
        },
        {
          "w": "a",
          "s": 356.062,
          "e": 356.159
        },
        {
          "w": "tiny",
          "s": 356.159,
          "e": 356.549
        },
        {
          "w": "star",
          "s": 356.549,
          "e": 356.94
        },
        {
          "w": "winking",
          "s": 356.94,
          "e": 357.622
        },
        {
          "w": "at",
          "s": 357.622,
          "e": 357.817
        },
        {
          "w": "you,",
          "s": 357.817,
          "e": 358.207
        },
        {
          "w": "you’ll",
          "s": 358.207,
          "e": 358.793
        },
        {
          "w": "know",
          "s": 358.793,
          "e": 359.183
        },
        {
          "w": "it’s",
          "s": 359.183,
          "e": 359.573
        },
        {
          "w": "Twink,",
          "s": 359.573,
          "e": 360.158
        },
        {
          "w": "reminding",
          "s": 360.158,
          "e": 361.036
        },
        {
          "w": "you",
          "s": 361.036,
          "e": 361.328
        },
        {
          "w": "that",
          "s": 361.328,
          "e": 361.719
        },
        {
          "w": "even",
          "s": 361.719,
          "e": 362.109
        },
        {
          "w": "the",
          "s": 362.109,
          "e": 362.401
        },
        {
          "w": "smallest",
          "s": 362.401,
          "e": 363.181
        },
        {
          "w": "light",
          "s": 363.181,
          "e": 363.669
        },
        {
          "w": "can",
          "s": 363.669,
          "e": 363.962
        },
        {
          "w": "make",
          "s": 363.962,
          "e": 364.352
        },
        {
          "w": "the",
          "s": 364.352,
          "e": 364.644
        },
        {
          "w": "biggest",
          "s": 364.644,
          "e": 365.327
        },
        {
          "w": "difference.",
          "s": 365.327,
          "e": 366.4
        }
      ]
    },
    {
      "text": "Now close your eyes, snuggle under your blankets, and dream of stars, sleigh bells, and the magic of Christmas Eve.",
      "side": "left",
      "start": 366.4,
      "end": 374.84,
      "image": "50_left.jpg",
      "words": [
        {
          "w": "Now",
          "s": 366.4,
          "e": 366.664
        },
        {
          "w": "close",
          "s": 366.664,
          "e": 367.103
        },
        {
          "w": "your",
          "s": 367.103,
          "e": 367.455
        },
        {
          "w": "eyes,",
          "s": 367.455,
          "e": 367.895
        },
        {
          "w": "snuggle",
          "s": 367.895,
          "e": 368.51
        },
        {
          "w": "under",
          "s": 368.51,
          "e": 368.95
        },
        {
          "w": "your",
          "s": 368.95,
          "e": 369.301
        },
        {
          "w": "blankets,",
          "s": 369.301,
          "e": 370.093
        },
        {
          "w": "and",
          "s": 370.093,
          "e": 370.356
        },
        {
          "w": "dream",
          "s": 370.356,
          "e": 370.796
        },
        {
          "w": "of",
          "s": 370.796,
          "e": 370.972
        },
        {
          "w": "stars,",
          "s": 370.972,
          "e": 371.499
        },
        {
          "w": "sleigh",
          "s": 371.499,
          "e": 372.027
        },
        {
          "w": "bells,",
          "s": 372.027,
          "e": 372.554
        },
        {
          "w": "and",
          "s": 372.554,
          "e": 372.818
        },
        {
          "w": "the",
          "s": 372.818,
          "e": 373.082
        },
        {
          "w": "magic",
          "s": 373.082,
          "e": 373.521
        },
        {
          "w": "of",
          "s": 373.521,
          "e": 373.697
        },
        {
          "w": "Christmas",
          "s": 373.697,
          "e": 374.488
        },
        {
          "w": "Eve.",
          "s": 374.488,
          "e": 374.84
        }
      ]
    }
  ]
}